tf_tagger/__init__.py
tf_tagger/tf_tagger.py
tf_tagger/version.txt
tf_tagger/models/__init__.py
tf_tagger/models/char_cnn.py
tf_tagger/models/crf.py
tf_tagger/models/decoder.py
tf_tagger/models/decoder_softmax.py
tf_tagger/models/embed.py
tf_tagger/models/encoder.py
tf_tagger/models/encoder_bert.py
tf_tagger/models/tagger_model.py
tf_tagger/test/__init__.py
tf_tagger/test/conll2003.py
tf_tagger/test/conll2003_bert.py
tf_tagger/test/conll2003_glove.py
tf_tagger/test/get_conll2003.py
tf_tagger/test/simple.py
tf_tagger/test/simple_bert.py
tf_tagger/utils/__init__.py
tf_tagger/utils/char_tokenizer.py
tf_tagger/utils/extract_entities.py
tf_tagger/utils/label.py
tf_tagger/utils/read_vectors.py
tf_tagger/utils/text_reader.py
tf_tagger/utils/tokenizer.py
tf_tagger-0.0.40.dist-info/LICENSE
tf_tagger-0.0.40.dist-info/METADATA
tf_tagger-0.0.40.dist-info/WHEEL
tf_tagger-0.0.40.dist-info/top_level.txt
tf_tagger-0.0.40.dist-info/RECORD
